setup.py
Windows7/__init__.py
Windows7.egg-info/PKG-INFO
Windows7.egg-info/SOURCES.txt
Windows7.egg-info/dependency_links.txt
Windows7.egg-info/top_level.txt